GradleShizhanZhongwenbanV10/README.md
GradleShizhanZhongwenbanV10/__init__.py
GradleShizhanZhongwenbanV10/__main__.py
GradleShizhanZhongwenbanV10/file.epub
GradleShizhanZhongwenbanV10/index.html
GradleShizhanZhongwenbanV10/css/__init__.py
GradleShizhanZhongwenbanV10/css/annotations.css
GradleShizhanZhongwenbanV10/css/main.css
GradleShizhanZhongwenbanV10/css/normalize.css
GradleShizhanZhongwenbanV10/css/popup.css
GradleShizhanZhongwenbanV10/font/__init__.py
GradleShizhanZhongwenbanV10/font/fontello.eot
GradleShizhanZhongwenbanV10/font/fontello.svg
GradleShizhanZhongwenbanV10/font/fontello.ttf
GradleShizhanZhongwenbanV10/font/fontello.woff
GradleShizhanZhongwenbanV10/img/__init__.py
GradleShizhanZhongwenbanV10/img/annotator-glyph-sprite.png
GradleShizhanZhongwenbanV10/img/annotator-icon-sprite.png
GradleShizhanZhongwenbanV10/img/apple-touch-icon.png
GradleShizhanZhongwenbanV10/img/cancelfullscreen.png
GradleShizhanZhongwenbanV10/img/close.png
GradleShizhanZhongwenbanV10/img/fullscreen.png
GradleShizhanZhongwenbanV10/img/loader.gif
GradleShizhanZhongwenbanV10/img/menu-icon.png
GradleShizhanZhongwenbanV10/img/save.png
GradleShizhanZhongwenbanV10/img/saved.png
GradleShizhanZhongwenbanV10/img/settings-s.png
GradleShizhanZhongwenbanV10/img/settings.png
GradleShizhanZhongwenbanV10/img/star.png
GradleShizhanZhongwenbanV10/js/__init__.py
GradleShizhanZhongwenbanV10/js/epub.js
GradleShizhanZhongwenbanV10/js/epub.min.js
GradleShizhanZhongwenbanV10/js/epub.min.map
GradleShizhanZhongwenbanV10/js/hooks.min.js
GradleShizhanZhongwenbanV10/js/hooks.min.map
GradleShizhanZhongwenbanV10/js/reader.js
GradleShizhanZhongwenbanV10/js/reader.js.map
GradleShizhanZhongwenbanV10/js/reader.min.js
GradleShizhanZhongwenbanV10/js/reader.min.map
GradleShizhanZhongwenbanV10/js/hooks/__init__.py
GradleShizhanZhongwenbanV10/js/hooks/extensions/__init__.py
GradleShizhanZhongwenbanV10/js/hooks/extensions/highlight.js
GradleShizhanZhongwenbanV10/js/libs/__init__.py
gradle_shizhan_zhongwenban_v1_0-2024.3.1.0.dist-info/METADATA
gradle_shizhan_zhongwenban_v1_0-2024.3.1.0.dist-info/WHEEL
gradle_shizhan_zhongwenban_v1_0-2024.3.1.0.dist-info/entry_points.txt
gradle_shizhan_zhongwenban_v1_0-2024.3.1.0.dist-info/top_level.txt
gradle_shizhan_zhongwenban_v1_0-2024.3.1.0.dist-info/RECORD
